<?xml version="1.0" encoding="UTF-8"?>
<settings>
  <language id="com.yourdomain.textile">
    <!-- Define what syntax this language should use;
          use the name of the syntax you define in Syntaxes -->
    <root-zone>language-root.jade</root-zone>
    <!-- Human readable name for the language -->
    <name>jade</name>

    <!-- Ways to detect the language (see next section) -->
    <detectors>
      <extension>jade</extension>
    </detectors>

    <!-- Only necessary if you support multiple extensions -->
    <default-extension>jade</default-extension>
  </language>  
</settings>